{"cameraMode":{"drawMode":0,"name":"Shaded","section":"Shading Mode"},"sceneLighting":true,"audioPlay":false,"sceneViewState":{"m_AlwaysRefresh":false,"showFog":true,"showSkybox":true,"showFlares":true,"showImageEffects":true,"showParticleSystems":true,"showVisualEffectGraphs":true,"m_FxEnabled":true},"in2DMode":false,"pivot":{"x":136.285888671875,"y":354.49066162109377,"z":-416.0706787109375},"rotation":{"x":0.26877376437187197,"y":-0.1744060218334198,"z":0.049347493797540668,"w":0.9455727934837341},"size":432.3857727050781,"orthographic":false}